[
    {
        "created_at": "2020-07-02 17:37:21.362687 UTC",
        "# Timestamp": "2020-07-02 17:13:19 UTC",
        "MMSI": 538004594,
        "msg_type": 1,
        "Latitude": -20.4266933333333,
        "Longitude": 58.3752,
        "SOG": 11.0,
        "COG": 237.2,
        "Heading": 235.0,
        "ROT": -10.0,
        "imo": 0.0,
        "name": 0,
        "call_sign": 0,
        "flag": "MH",
        "draught": 0.0,
        "ship_and_cargo_type": 0.0,
        "length": 0.0,
        "width": 0.0,
        "eta": 0,
        "destination": 0,
        "status": 0.0,
        "maneuver": 0.0,
        "accuracy": 1.0,
        "collection_type": "satellite",
        "mmsi_label": "mmsi-538004594"
    },
    {
        "created_at": "2020-07-02 17:37:21.362687 UTC",
        "# Timestamp": "2020-07-02 17:13:28 UTC",
        "MMSI": 538004594,
        "msg_type": 1,
        "Latitude": -20.4269333333333,
        "Longitude": 58.3747733333333,
        "SOG": 11.0,
        "COG": 239.7,
        "Heading": 235.0,
        "ROT": -7.0,
        "imo": 0.0,
        "name": 0,
        "call_sign": 0,
        "flag": "MH",
        "draught": 0.0,
        "ship_and_cargo_type": 0.0,
        "length": 0.0,
        "width": 0.0,
        "eta": 0,
        "destination": 0,
        "status": 0.0,
        "maneuver": 0.0,
        "accuracy": 1.0,
        "collection_type": "satellite",
        "mmsi_label": "mmsi-538004594"
    },
    {
        "created_at": "2020-07-02 17:37:21.362687 UTC",
        "# Timestamp": "2020-07-02 17:13:38 UTC",
        "MMSI": 538004594,
        "msg_type": 1,
        "Latitude": -20.4271733333333,
        "Longitude": 58.37432,
        "SOG": 11.0,
        "COG": 239.2,
        "Heading": 235.0,
        "ROT": -8.0,
        "imo": 0.0,
        "name": 0,
        "call_sign": 0,
        "flag": "MH",
        "draught": 0.0,
        "ship_and_cargo_type": 0.0,
        "length": 0.0,
        "width": 0.0,
        "eta": 0,
        "destination": 0,
        "status": 0.0,
        "maneuver": 0.0,
        "accuracy": 1.0,
        "collection_type": "satellite",
        "mmsi_label": "mmsi-538004594"
    },
    {
        "created_at": "2020-07-02 17:37:15.496847 UTC",
        "# Timestamp": "2020-07-02 17:14:28 UTC",
        "MMSI": 538004594,
        "msg_type": 1,
        "Latitude": -20.42856,
        "Longitude": 58.372,
        "SOG": 11.1,
        "COG": 239.0,
        "Heading": 235.0,
        "ROT": -9.0,
        "imo": 0.0,
        "name": 0,
        "call_sign": 0,
        "flag": "MH",
        "draught": 0.0,
        "ship_and_cargo_type": 0.0,
        "length": 0.0,
        "width": 0.0,
        "eta": 0,
        "destination": 0,
        "status": 0.0,
        "maneuver": 0.0,
        "accuracy": 1.0,
        "collection_type": "satellite",
        "mmsi_label": "mmsi-538004594"
    },
    {
        "created_at": "2020-07-02 21:55:05.260646 UTC",
        "# Timestamp": "2020-07-02 20:17:45 UTC",
        "MMSI": 538004594,
        "msg_type": 5,
        "Latitude": 0.0,
        "Longitude": 0.0,
        "SOG": 0.0,
        "COG": 0.0,
        "Heading": 0.0,
        "ROT": 0.0,
        "imo": 9601235.0,
        "name": "DENSA ORCA",
        "call_sign": "V7XX5",
        "flag": "MH",
        "draught": 9.4,
        "ship_and_cargo_type": 80.0,
        "length": 274.0,
        "width": 48.0,
        "eta": "2020-07-16 13:00:00 UTC",
        "destination": "AO MAL",
        "status": 0.0,
        "maneuver": 0.0,
        "accuracy": 0.0,
        "collection_type": "satellite",
        "mmsi_label": "mmsi-538004594"
    }
]